experiment_replay/__init__.py
experiment_replay/__main__.py
pytorch_replay/__init__.py
pytorch_replay/__main__.py
experiment_replay-0.0.1.dist-info/LICENSE
experiment_replay-0.0.1.dist-info/METADATA
experiment_replay-0.0.1.dist-info/WHEEL
experiment_replay-0.0.1.dist-info/top_level.txt
experiment_replay-0.0.1.dist-info/RECORD
