Metadata-Version: 2.1
Name: experiment-replay
Version: 0.0.1
Summary: Make running, replaying experiments easier either on Pytorch or Tensorflow
Home-page: https://github.com/Narsil/experiment_replay
Author: Nicolas Patry
Author-email: patry.nicolas@protonmail.com
License: UNKNOWN
Platform: UNKNOWN
Classifier: Programming Language :: Python :: 3
Classifier: License :: OSI Approved :: MIT License
Classifier: Operating System :: OS Independent
